NST_Scrape/__init__.py
NST_Scrape/nst_scraper.py
NST_Scrape-1.0.1.dist-info/LICENSE
NST_Scrape-1.0.1.dist-info/METADATA
NST_Scrape-1.0.1.dist-info/WHEEL
NST_Scrape-1.0.1.dist-info/top_level.txt
NST_Scrape-1.0.1.dist-info/RECORD
