Metadata-Version: 2.1
Name: NST_Scrape
Version: 1.0.1
Summary: A Python Package for scraping National Hockey League information and stats from Natural Stat Trick.
Author-email: Owen Singh <owenbksingh@gmail.com>
Project-URL: Homepage, https://github.com/owensingh38/wsba_nhl_shot_impact/
Classifier: Programming Language :: Python :: 3
Classifier: License :: OSI Approved :: MIT License
Classifier: Operating System :: OS Independent
Requires-Python: >=3.8
License-File: LICENSE
